<?xml version="1.0" encoding="UTF-8"?>
<WorkflowDefinitions creationDate="2026-05-13T13:07:03Z" versionNumber="2026.05.9.6f185fa">
   <WorkflowDefinition version="1">
      <Name>WF_5165_GestionPrixAchat_OA</Name>
      <Description>Mis à jour du prix d'achat OA sure la modification de l'indice
Creation Date: 08/05/2026
Updated Date: 
Version: 1.0</Description>
      <LastUpdatedBy>Assootosh Motah</LastUpdatedBy>
      <Variables>
         <Variable>
            <Name>SUNO</Name>
            <DataType>String</DataType>
            <IsWorkflowInput>False</IsWorkflowInput>
            <IsWorkflowOutput>False</IsWorkflowOutput>
            <IsUseValue>False</IsUseValue>
         </Variable>
         <Variable>
            <Name>ITNO</Name>
            <DataType>String</DataType>
            <IsWorkflowInput>False</IsWorkflowInput>
            <IsWorkflowOutput>False</IsWorkflowOutput>
            <IsUseValue>False</IsUseValue>
         </Variable>
         <Variable>
            <Name>OURR</Name>
            <DataType>String</DataType>
            <IsWorkflowInput>False</IsWorkflowInput>
            <IsWorkflowOutput>False</IsWorkflowOutput>
            <IsUseValue>False</IsUseValue>
         </Variable>
         <Variable>
            <Name>APIFLOWOut</Name>
            <DataType>String</DataType>
            <IsWorkflowInput>False</IsWorkflowInput>
            <IsWorkflowOutput>False</IsWorkflowOutput>
            <IsUseValue>False</IsUseValue>
         </Variable>
         <Variable>
            <Name>UCA9</Name>
            <DataType>String</DataType>
            <IsWorkflowInput>False</IsWorkflowInput>
            <IsWorkflowOutput>False</IsWorkflowOutput>
            <InitialValue/>
            <IsUseValue>False</IsUseValue>
         </Variable>
         <Variable>
            <Name>PUNO</Name>
            <DataType>String</DataType>
            <IsWorkflowInput>True</IsWorkflowInput>
            <IsWorkflowOutput>False</IsWorkflowOutput>
            <IsUseValue>False</IsUseValue>
         </Variable>
         <Variable>
            <Name>PNLI</Name>
            <DataType>String</DataType>
            <IsWorkflowInput>True</IsWorkflowInput>
            <IsWorkflowOutput>False</IsWorkflowOutput>
            <IsUseValue>False</IsUseValue>
         </Variable>
         <Variable>
            <Name>PUDT</Name>
            <DataType>String</DataType>
            <IsWorkflowInput>False</IsWorkflowInput>
            <IsWorkflowOutput>False</IsWorkflowOutput>
            <InitialValue/>
            <IsUseValue>False</IsUseValue>
         </Variable>
         <Variable>
            <Name>PNLS</Name>
            <DataType>String</DataType>
            <IsWorkflowInput>True</IsWorkflowInput>
            <IsWorkflowOutput>False</IsWorkflowOutput>
            <IsUseValue>False</IsUseValue>
         </Variable>
      </Variables>
      <Views/>
      <WorkFlowTrees/>
      <DistributionItems>
         <DistributionItem>
            <Id>887</Id>
            <Type>Person</Type>
            <Name>3c71edba-59a3-40c7-847e-3e8211e7bb5f</Name>
            <Description>Assootosh Motah</Description>
            <SendEmail>False</SendEmail>
         </DistributionItem>
      </DistributionItems>
      <WorkflowDecisionTables/>
      <SequentialFlow>
         <SequenceNumber>0</SequenceNumber>
         <FlowParts>
            <FlowPart type="IonApiExitPoint">
               <SequenceNumber>1</SequenceNumber>
               <Name>GetHead</Name>
               <RetryTime>600</RetryTime>
               <TimeOut>600</TimeOut>
               <IgnoreErrors>True</IgnoreErrors>
               <IonApiMethod>{"productLogicalId":"infor.m3","operationProxyPath":"M3/m3api-rest/v2/execute/PPS200MI","operationRestPath":"/GetHead","productName":"M3","operationPath":"M3/m3api-rest/v2/execute/PPS200MI/GetHead","summary":"Get a purchase order head","httpMethod":"GET","availableOutputContentTypes":["JSON"],"outputContentType":"JSON","input":[{"wfVariableName":"PUNO","literalValue":null,"name":"PUNO","description":"Purchase order number(10)","swaggerDatatype":"string","swaggerFormat":null,"required":true,"type":"QUERY"},{"wfVariableName":null,"literalValue":null,"name":"CONO","description":"Company(3)","swaggerDatatype":"number","swaggerFormat":null,"required":false,"type":"QUERY"},{"wfVariableName":null,"literalValue":null,"name":"cono","description":"The company context to use. Defaults to user default","swaggerDatatype":"string","swaggerFormat":null,"required":false,"type":"QUERY"},{"wfVariableName":null,"literalValue":null,"name":"divi","description":"The division context to use. Defaults to user default","swaggerDatatype":"string","swaggerFormat":null,"required":false,"type":"QUERY"},{"wfVariableName":null,"literalValue":null,"name":"lanc","description":"The language code to use. Defaults to user default","swaggerDatatype":"string","swaggerFormat":null,"required":false,"type":"QUERY"},{"wfVariableName":null,"literalValue":null,"name":"locale","description":"The locale to use","swaggerDatatype":"string","swaggerFormat":null,"required":false,"type":"QUERY"},{"wfVariableName":null,"literalValue":null,"name":"timeZone","description":"The time zone to use","swaggerDatatype":"string","swaggerFormat":null,"required":false,"type":"QUERY"},{"wfVariableName":null,"literalValue":null,"name":"maxrecs","description":"Max number of records returned. 0 is unlimited","swaggerDatatype":"string","swaggerFormat":null,"required":false,"type":"QUERY"},{"wfVariableName":null,"literalValue":null,"name":"dateformat","description":"Date format to use","swaggerDatatype":"string","swaggerFormat":null,"required":false,"type":"QUERY"},{"wfVariableName":null,"literalValue":null,"name":"excludeempty","description":"When true, empty fields are omitted in response","swaggerDatatype":"string","swaggerFormat":null,"required":false,"type":"QUERY"},{"wfVariableName":null,"literalValue":null,"name":"righttrim","description":"When true, all values are right trimmed in response","swaggerDatatype":"string","swaggerFormat":null,"required":false,"type":"QUERY"},{"wfVariableName":null,"literalValue":null,"name":"returncols","description":"A comma separated list of column names that should be included in the response. Defaults to all columns","swaggerDatatype":"string","swaggerFormat":null,"required":false,"type":"QUERY"},{"wfVariableName":null,"literalValue":null,"name":"format","description":"Controls output JSON format","swaggerDatatype":"string","swaggerFormat":null,"required":false,"type":"QUERY"},{"wfVariableName":null,"literalValue":null,"name":"extendedresult","description":"Show transaction parameters in the response","swaggerDatatype":"string","swaggerFormat":null,"required":false,"type":"QUERY"},{"wfVariableName":null,"literalValue":null,"name":"positionkey","description":"The position in a table to start reading from","swaggerDatatype":"string","swaggerFormat":null,"required":false,"type":"HEADER"}],"output":[{"wfVariableName":"PUDT","type":"BODY","path":"$.results[0].records[0].PUDT","optional":false}],"inputBody":{"name":null,"description":null,"required":false,"availableInputContentTypes":[],"inputContentType":null,"body":" ","ignore":true,"structureNamesFromBody":[],"variableNamesFromBody":[]}}</IonApiMethod>
               <IsCustom>False</IsCustom>
            </FlowPart>
            <FlowPart type="UserTask">
               <SequenceNumber>4</SequenceNumber>
               <Name>Notification 1</Name>
               <SummaryMessage>[APIFLOWOut][ITNO][OURR][PNLI][PNLS][PUDT][PUNO][SUNO][UCA9]</SummaryMessage>
               <Priority>Medium</Priority>
               <IsParallel>False</IsParallel>
               <TaskActionType>StandardAction</TaskActionType>
               <UserTaskType>NOTIFICATION</UserTaskType>
               <MaxEscalationLevel>1</MaxEscalationLevel>
               <DistributionComplexity>simple</DistributionComplexity>
               <DistributionItemIds>
                  <DistributionItemId>887</DistributionItemId>
               </DistributionItemIds>
               <Parameters>
                  <Parameter>
                     <Label>SUNO</Label>
                     <VariableName>SUNO</VariableName>
                     <ReadOnly>True</ReadOnly>
                     <SequenceNumber>7</SequenceNumber>
                     <CompletionProperty>NotApplicable</CompletionProperty>
                     <Labels/>
                  </Parameter>
                  <Parameter>
                     <Label>PUNO</Label>
                     <VariableName>PUNO</VariableName>
                     <ReadOnly>True</ReadOnly>
                     <SequenceNumber>6</SequenceNumber>
                     <CompletionProperty>NotApplicable</CompletionProperty>
                     <Labels/>
                  </Parameter>
                  <Parameter>
                     <Label>ITNO</Label>
                     <VariableName>ITNO</VariableName>
                     <ReadOnly>True</ReadOnly>
                     <SequenceNumber>1</SequenceNumber>
                     <CompletionProperty>NotApplicable</CompletionProperty>
                     <Labels/>
                  </Parameter>
                  <Parameter>
                     <Label>PNLI</Label>
                     <VariableName>PNLI</VariableName>
                     <ReadOnly>True</ReadOnly>
                     <SequenceNumber>3</SequenceNumber>
                     <CompletionProperty>NotApplicable</CompletionProperty>
                     <Labels/>
                  </Parameter>
                  <Parameter>
                     <Label>OURR</Label>
                     <VariableName>OURR</VariableName>
                     <ReadOnly>True</ReadOnly>
                     <SequenceNumber>2</SequenceNumber>
                     <CompletionProperty>NotApplicable</CompletionProperty>
                     <Labels/>
                  </Parameter>
                  <Parameter>
                     <Label>APIFLOWOut</Label>
                     <VariableName>APIFLOWOut</VariableName>
                     <ReadOnly>True</ReadOnly>
                     <SequenceNumber>0</SequenceNumber>
                     <CompletionProperty>NotApplicable</CompletionProperty>
                     <Labels/>
                  </Parameter>
                  <Parameter>
                     <Label>PNLS</Label>
                     <VariableName>PNLS</VariableName>
                     <ReadOnly>True</ReadOnly>
                     <SequenceNumber>4</SequenceNumber>
                     <CompletionProperty>NotApplicable</CompletionProperty>
                     <Labels/>
                  </Parameter>
                  <Parameter>
                     <Label>PUDT</Label>
                     <VariableName>PUDT</VariableName>
                     <ReadOnly>True</ReadOnly>
                     <SequenceNumber>5</SequenceNumber>
                     <CompletionProperty>NotApplicable</CompletionProperty>
                     <Labels/>
                  </Parameter>
                  <Parameter>
                     <Label>UCA9</Label>
                     <VariableName>UCA9</VariableName>
                     <ReadOnly>True</ReadOnly>
                     <SequenceNumber>8</SequenceNumber>
                     <CompletionProperty>NotApplicable</CompletionProperty>
                     <Labels/>
                  </Parameter>
               </Parameters>
               <ActionButtons/>
               <TaskMessages/>
               <Escalations/>
               <WorkflowDecisionTableIds/>
               <PropagateNotes>False</PropagateNotes>
            </FlowPart>
            <FlowPart type="IonApiExitPoint">
               <SequenceNumber>3</SequenceNumber>
               <Name>API Flow</Name>
               <RetryTime>600</RetryTime>
               <TimeOut>600</TimeOut>
               <IgnoreErrors>False</IgnoreErrors>
               <IonApiMethod>{"productLogicalId":"inforos.apiflows","operationProxyPath":"APIFLOWS/5165","operationRestPath":"/GPA","productName":"Infor API Flows","operationPath":"APIFLOWS/5165/GPA","summary":"","httpMethod":"POST","availableOutputContentTypes":["JSON"],"outputContentType":"JSON","input":[{"wfVariableName":"UCA9","literalValue":null,"name":"reve","description":"Indice OA/POA","swaggerDatatype":"string","swaggerFormat":null,"required":true,"type":"HEADER"},{"wfVariableName":"PUDT","literalValue":null,"name":"date","description":"Date OA/POA pour comparison","swaggerDatatype":"string","swaggerFormat":null,"required":true,"type":"HEADER"},{"wfVariableName":"OURR","literalValue":null,"name":"ourr","description":"Agreeement Number","swaggerDatatype":"string","swaggerFormat":null,"required":true,"type":"HEADER"},{"wfVariableName":"ITNO","literalValue":null,"name":"itno","description":"Numéro d'artice","swaggerDatatype":"string","swaggerFormat":null,"required":true,"type":"HEADER"},{"wfVariableName":"SUNO","literalValue":null,"name":"suno","description":"Numéro fournisseur","swaggerDatatype":"string","swaggerFormat":null,"required":true,"type":"HEADER"},{"wfVariableName":"PUNO","literalValue":null,"name":"puno","description":"","swaggerDatatype":"string","swaggerFormat":null,"required":true,"type":"HEADER"},{"wfVariableName":"PNLI","literalValue":null,"name":"pnli","description":null,"swaggerDatatype":"string","swaggerFormat":null,"required":true,"type":"HEADER"},{"wfVariableName":"PNLS","literalValue":null,"name":"pnls","description":null,"swaggerDatatype":"string","swaggerFormat":null,"required":true,"type":"HEADER"},{"wfVariableName":null,"literalValue":"1","name":"flag","description":"1 = OA , 2 = POA","swaggerDatatype":"string","swaggerFormat":null,"required":true,"type":"HEADER"},{"wfVariableName":null,"literalValue":null,"name":"ionapiRespStyle","description":"Indicate to execute synchronously or asynchronously","swaggerDatatype":"string","swaggerFormat":null,"required":false,"type":"QUERY"}],"output":[{"wfVariableName":"APIFLOWOut","type":"BODY","path":"$","optional":false}],"inputBody":{"name":null,"description":null,"required":false,"availableInputContentTypes":[],"inputContentType":null,"body":" ","ignore":true,"structureNamesFromBody":[],"variableNamesFromBody":[]}}</IonApiMethod>
               <IsCustom>False</IsCustom>
            </FlowPart>
            <FlowPart type="IonApiExitPoint">
               <SequenceNumber>2</SequenceNumber>
               <Name>GetLine</Name>
               <Description>Recuperation ligne OA</Description>
               <RetryTime>600</RetryTime>
               <TimeOut>600</TimeOut>
               <IgnoreErrors>False</IgnoreErrors>
               <IonApiMethod>{"productLogicalId":"infor.m3","operationProxyPath":"M3/m3api-rest/v2/execute/PPS200MI","operationRestPath":"/GetLine","productName":"M3","operationPath":"M3/m3api-rest/v2/execute/PPS200MI/GetLine","summary":"Get a purchase order line","httpMethod":"GET","availableOutputContentTypes":["JSON"],"outputContentType":"JSON","input":[{"wfVariableName":"PUNO","literalValue":null,"name":"PUNO","description":"Purchase order number(10)","swaggerDatatype":"string","swaggerFormat":null,"required":true,"type":"QUERY"},{"wfVariableName":null,"literalValue":null,"name":"CONO","description":"Company(3)","swaggerDatatype":"number","swaggerFormat":null,"required":false,"type":"QUERY"},{"wfVariableName":"PNLI","literalValue":null,"name":"PNLI","description":"Purchase order line(3)","swaggerDatatype":"number","swaggerFormat":null,"required":false,"type":"QUERY"},{"wfVariableName":"PNLS","literalValue":null,"name":"PNLS","description":"Purchase order line subnumber(3)","swaggerDatatype":"number","swaggerFormat":null,"required":false,"type":"QUERY"},{"wfVariableName":null,"literalValue":null,"name":"cono","description":"The company context to use. Defaults to user default","swaggerDatatype":"string","swaggerFormat":null,"required":false,"type":"QUERY"},{"wfVariableName":null,"literalValue":null,"name":"divi","description":"The division context to use. Defaults to user default","swaggerDatatype":"string","swaggerFormat":null,"required":false,"type":"QUERY"},{"wfVariableName":null,"literalValue":null,"name":"lanc","description":"The language code to use. Defaults to user default","swaggerDatatype":"string","swaggerFormat":null,"required":false,"type":"QUERY"},{"wfVariableName":null,"literalValue":null,"name":"locale","description":"The locale to use","swaggerDatatype":"string","swaggerFormat":null,"required":false,"type":"QUERY"},{"wfVariableName":null,"literalValue":null,"name":"timeZone","description":"The time zone to use","swaggerDatatype":"string","swaggerFormat":null,"required":false,"type":"QUERY"},{"wfVariableName":null,"literalValue":null,"name":"maxrecs","description":"Max number of records returned. 0 is unlimited","swaggerDatatype":"string","swaggerFormat":null,"required":false,"type":"QUERY"},{"wfVariableName":null,"literalValue":null,"name":"dateformat","description":"Date format to use","swaggerDatatype":"string","swaggerFormat":null,"required":false,"type":"QUERY"},{"wfVariableName":null,"literalValue":null,"name":"excludeempty","description":"When true, empty fields are omitted in response","swaggerDatatype":"string","swaggerFormat":null,"required":false,"type":"QUERY"},{"wfVariableName":null,"literalValue":null,"name":"righttrim","description":"When true, all values are right trimmed in response","swaggerDatatype":"string","swaggerFormat":null,"required":false,"type":"QUERY"},{"wfVariableName":null,"literalValue":null,"name":"returncols","description":"A comma separated list of column names that should be included in the response. Defaults to all columns","swaggerDatatype":"string","swaggerFormat":null,"required":false,"type":"QUERY"},{"wfVariableName":null,"literalValue":null,"name":"format","description":"Controls output JSON format","swaggerDatatype":"string","swaggerFormat":null,"required":false,"type":"QUERY"},{"wfVariableName":null,"literalValue":null,"name":"extendedresult","description":"Show transaction parameters in the response","swaggerDatatype":"string","swaggerFormat":null,"required":false,"type":"QUERY"},{"wfVariableName":null,"literalValue":null,"name":"positionkey","description":"The position in a table to start reading from","swaggerDatatype":"string","swaggerFormat":null,"required":false,"type":"HEADER"}],"output":[{"wfVariableName":"UCA9","type":"BODY","path":"$.results[0].records[0].UCA9","optional":false},{"wfVariableName":"ITNO","type":"BODY","path":"$.results[0].records[0].ITNO","optional":false},{"wfVariableName":"SUNO","type":"BODY","path":"$.results[0].records[0].SUNO","optional":false},{"wfVariableName":"OURR","type":"BODY","path":"$.results[0].records[0].OURR","optional":false}],"inputBody":{"name":null,"description":null,"required":false,"availableInputContentTypes":[],"inputContentType":null,"body":" ","ignore":true,"structureNamesFromBody":[],"variableNamesFromBody":[]}}</IonApiMethod>
               <IsCustom>False</IsCustom>
            </FlowPart>
         </FlowParts>
      </SequentialFlow>
   </WorkflowDefinition>
</WorkflowDefinitions>
